policy_priority_inference/__init__.py
policy_priority_inference/policy_priority_inference.py
policy_priority_inference-3.0.5.dist-info/METADATA
policy_priority_inference-3.0.5.dist-info/WHEEL
policy_priority_inference-3.0.5.dist-info/licenses/LICENSE
policy_priority_inference-3.0.5.dist-info/RECORD
