Metadata-Version: 2.3
Name: policy_priority_inference
Version: 3.0.5
Summary: The model of the Policy Priority Inference impact-evaluation toolkit and its calibration algorithm.
Project-URL: Homepage, https://policypriority.org
Project-URL: Issues, https://github.com/oguerrer/ppi
Author-email: "Omar A. Guerrero" <oguerrer@gmail.com>
License-File: LICENSE
Classifier: Intended Audience :: Science/Research
Classifier: License :: OSI Approved :: MIT License
Classifier: Operating System :: OS Independent
Classifier: Programming Language :: Python :: 3
Classifier: Topic :: Scientific/Engineering :: Artificial Intelligence
Requires-Python: >=3.11
